parserator/__init__.py
parserator/data_prep_utils.py
parserator/main.py
parserator/manual_labeling.py
parserator/parser_template.py
parserator/spotcheck.py
parserator/training.py
parserator-0.6.9.dist-info/LICENSE
parserator-0.6.9.dist-info/METADATA
parserator-0.6.9.dist-info/WHEEL
parserator-0.6.9.dist-info/entry_points.txt
parserator-0.6.9.dist-info/top_level.txt
parserator-0.6.9.dist-info/RECORD
